feeds/__init__.py
feeds/admin.py
feeds/apps.py
feeds/models.py
feeds/tests.py
feeds/utils.py
feeds/utils_internal.py
feeds/views.py
feeds/management/__init__.py
feeds/management/commands/__init__.py
feeds/management/commands/refreshfeeds.py
feeds/migrations/0001_initial.py
feeds/migrations/0002_auto_20190604_0845.py
feeds/migrations/0003_post_image_url.py
feeds/migrations/0004_webproxy.py
feeds/migrations/0005_source_description.py
feeds/migrations/0006_auto_20190901_1644.py
feeds/migrations/0007_auto_20210502_0716.py
feeds/migrations/0008_allow_longer_post_guid.py
feeds/migrations/0009_allow_source_last_change_and_last_success_to_be_blank.py
feeds/migrations/0010_enclosure_description_enclosure_medium.py
feeds/migrations/0011_alter_post_guid.py
feeds/migrations/0012_source_last_read_subscription.py
feeds/migrations/0013_delete_webproxy_enclosure_is_current.py
feeds/migrations/0014_post_json_source_json.py
feeds/migrations/0015_source_alt_url.py
feeds/migrations/__init__.py
django_feed_reader-2.0.0.dist-info/LICENSE
django_feed_reader-2.0.0.dist-info/METADATA
django_feed_reader-2.0.0.dist-info/WHEEL
django_feed_reader-2.0.0.dist-info/top_level.txt
django_feed_reader-2.0.0.dist-info/RECORD
