Metadata-Version: 2.1
Name: django-feed-reader
Version: 2.0.0
Summary: An RSS feed reading library for Django.
Home-page: https://github.com/xurble/django-feed-reader
Author: Gareth Simpson
Author-email: g@xurble.org
License: MIT
Classifier: Programming Language :: Python :: 3
Classifier: License :: OSI Approved :: MIT License
Classifier: Operating System :: OS Independent
License-File: LICENSE
Requires-Dist: dripfeed-client
Requires-Dist: sgmllib3k
Requires-Dist: requests
Requires-Dist: feedparser >=6.0.0
Requires-Dist: beautifulsoup4
Requires-Dist: pyrfc3339
Requires-Dist: Django >=2.2
